<annotation>
	<folder>train</folder>
	<filename>11_02_01.png</filename>
	<path>C:\Users\Aruts\Documents\Tensorflow\workspace\training_demo\images\train\11_02_01.png</path>
	<source>
		<database>Unknown</database>
	</source>
	<size>
		<width>128</width>
		<height>128</height>
		<depth>1</depth>
	</size>
	<segmented>0</segmented>
	<object>
		<name>corrosion</name>
		<pose>Unspecified</pose>
		<truncated>0</truncated>
		<difficult>0</difficult>
		<bndbox>
			<xmin>90</xmin>
			<ymin>72</ymin>
			<xmax>97</xmax>
			<ymax>80</ymax>
		</bndbox>
	</object>
	<object>
		<name>corrosion</name>
		<pose>Unspecified</pose>
		<truncated>0</truncated>
		<difficult>0</difficult>
		<bndbox>
			<xmin>87</xmin>
			<ymin>56</ymin>
			<xmax>91</xmax>
			<ymax>60</ymax>
		</bndbox>
	</object>
	<object>
		<name>corrosion</name>
		<pose>Unspecified</pose>
		<truncated>1</truncated>
		<difficult>0</difficult>
		<bndbox>
			<xmin>109</xmin>
			<ymin>1</ymin>
			<xmax>122</xmax>
			<ymax>10</ymax>
		</bndbox>
	</object>
</annotation>
