<annotation>
	<folder>train</folder>
	<filename>19_03_03.png</filename>
	<path>C:\Users\Aruts\Documents\Tensorflow\workspace\training_demo\images\train\19_03_03.png</path>
	<source>
		<database>Unknown</database>
	</source>
	<size>
		<width>128</width>
		<height>128</height>
		<depth>1</depth>
	</size>
	<segmented>0</segmented>
	<object>
		<name>corrosion</name>
		<pose>Unspecified</pose>
		<truncated>0</truncated>
		<difficult>0</difficult>
		<bndbox>
			<xmin>23</xmin>
			<ymin>8</ymin>
			<xmax>31</xmax>
			<ymax>16</ymax>
		</bndbox>
	</object>
	<object>
		<name>corrosion</name>
		<pose>Unspecified</pose>
		<truncated>0</truncated>
		<difficult>0</difficult>
		<bndbox>
			<xmin>65</xmin>
			<ymin>21</ymin>
			<xmax>71</xmax>
			<ymax>27</ymax>
		</bndbox>
	</object>
	<object>
		<name>corrosion</name>
		<pose>Unspecified</pose>
		<truncated>0</truncated>
		<difficult>0</difficult>
		<bndbox>
			<xmin>78</xmin>
			<ymin>29</ymin>
			<xmax>85</xmax>
			<ymax>36</ymax>
		</bndbox>
	</object>
	<object>
		<name>corrosion</name>
		<pose>Unspecified</pose>
		<truncated>1</truncated>
		<difficult>0</difficult>
		<bndbox>
			<xmin>1</xmin>
			<ymin>111</ymin>
			<xmax>8</xmax>
			<ymax>120</ymax>
		</bndbox>
	</object>
	<object>
		<name>corrosion</name>
		<pose>Unspecified</pose>
		<truncated>0</truncated>
		<difficult>0</difficult>
		<bndbox>
			<xmin>16</xmin>
			<ymin>110</ymin>
			<xmax>24</xmax>
			<ymax>116</ymax>
		</bndbox>
	</object>
	<object>
		<name>corrosion</name>
		<pose>Unspecified</pose>
		<truncated>0</truncated>
		<difficult>0</difficult>
		<bndbox>
			<xmin>80</xmin>
			<ymin>114</ymin>
			<xmax>87</xmax>
			<ymax>122</ymax>
		</bndbox>
	</object>
</annotation>
